[
	{
		"title": "pincel",
		"description": "elemento para pintar",
		"price": 20,
		"thumbnail": "direccion",
		"code": 124,
		"stock": 10,
		"id": 1
	},
	{
		"title": "tijera",
		"description": "elemento para cortar",
		"price": 20,
		"thumbnail": "direccion",
		"code": 123,
		"stock": 10,
		"id": 2
	},
	{
		"title": "liquid",
		"description": "elemento para borrar",
		"price": 20,
		"thumbnail": "direccion",
		"code": 122,
		"stock": 10,
		"id": 3
	},
	{
		"title": "goma",
		"description": "elemento para borrar",
		"price": 12,
		"thumbnail": "direccion",
		"code": 126,
		"stock": 10,
		"id": 4
	},
	{
		"title": "sello",
		"description": "elemento para sellar",
		"price": 200,
		"thumbnail": "direccion",
		"code": 125,
		"stock": 230,
		"id": 5
	}
]